rescaler
