Metadata-Version: 2.1
Name: rescaler
Version: 0.0.2
Summary: Transform features by scaling each feature to a given range.
Home-page: https://github.com/xga0/rescale-package
Author: Sean Gao
Author-email: seangaoxy@gmail.com
License: UNKNOWN
Platform: UNKNOWN
Classifier: Programming Language :: Python :: 3
Classifier: License :: OSI Approved :: MIT License
Classifier: Operating System :: OS Independent
Requires-Python: >=3.6
